./.gitignore
./.pre-commit-config.yaml
./.python-version
./PKG-INFO
./README.md
./py.typed
./pyproject.toml
./tinymsg.py
./tinymsg.pyi
./uv.lock
./scripts/deploy.sh
./tests/__init__.py
./tests/test_tinymsg.py
tinymsg-0.1.2.dist-info/METADATA
tinymsg-0.1.2.dist-info/WHEEL
tinymsg-0.1.2.dist-info/RECORD
