Metadata-Version: 2.4
Name: tinymsg
Version: 0.1.2
Summary: A lightweight serialization library for Python using MessagePack with type-safe Pydantic models
Project-URL: source, https://github.com/alangshur/tinymsg
Author-email: Alex Langshur <alex@langshur.com>
License: MIT
Requires-Python: >=3.13
Requires-Dist: msgpack>=1.0.0
Requires-Dist: pydantic>=2.0.0
